m_pyside/__init__.py
m_pyside/modules/__init__.py
m_pyside/modules/dataclass.py
m_pyside/qss/photo_card.css
m_pyside/resources/abc_logo.png
m_pyside/resources/arrow-d.png
m_pyside/resources/arrow-l.png
m_pyside/resources/arrow-r.png
m_pyside/resources/arrow-u.png
m_pyside/resources/ass_logo.png
m_pyside/resources/dir.png
m_pyside/resources/fbx_logo.png
m_pyside/resources/maya.jpg
m_pyside/resources/sp.png
m_pyside/util.py
m_pyside/widgets/__init__.py
m_pyside/widgets/collapsible.py
m_pyside/widgets/file_list.py
m_pyside/widgets/photo_card.py
m_pyside/widgets/photo_fluid_card.py
m_pyside-0.2.3.dist-info/METADATA
m_pyside-0.2.3.dist-info/WHEEL
m_pyside-0.2.3.dist-info/RECORD
